mauth_client/__init__.py
mauth_client/authenticator.py
mauth_client/config.py
mauth_client/consts.py
mauth_client/exceptions.py
mauth_client/httpx_mauth/__init__.py
mauth_client/httpx_mauth/client.py
mauth_client/key_holder.py
mauth_client/lambda_authenticator/__init__.py
mauth_client/lambda_authenticator/lambda_authenticator.py
mauth_client/lambda_helper.py
mauth_client/middlewares/__init__.py
mauth_client/middlewares/asgi.py
mauth_client/middlewares/wsgi.py
mauth_client/requests_mauth/__init__.py
mauth_client/requests_mauth/client.py
mauth_client/rsa_signer.py
mauth_client/rsa_verifier.py
mauth_client/signable.py
mauth_client/signed.py
mauth_client/signer.py
mauth_client/utils.py
mauth_client-1.8.0.dist-info/METADATA
mauth_client-1.8.0.dist-info/WHEEL
mauth_client-1.8.0.dist-info/licenses/LICENSE.txt
mauth_client-1.8.0.dist-info/RECORD
