Metadata-Version: 2.4
Name: mauth-client
Version: 1.8.0
Summary: MAuth Client for Python
License: MIT
License-File: LICENSE.txt
Author: Medidata Solutions
Author-email: support@mdsol.com
Requires-Python: >=3.9,<4.0
Classifier: Development Status :: 3 - Alpha
Classifier: Environment :: Web Environment
Classifier: Intended Audience :: Developers
Classifier: License :: OSI Approved :: MIT License
Classifier: Operating System :: OS Independent
Classifier: Programming Language :: Python
Classifier: Programming Language :: Python :: 3
Classifier: Programming Language :: Python :: 3.9
Classifier: Programming Language :: Python :: 3.10
Classifier: Programming Language :: Python :: 3.11
Classifier: Programming Language :: Python :: 3.12
Classifier: Programming Language :: Python :: 3.13
Classifier: Programming Language :: Python :: 3.14
Classifier: Topic :: Internet :: WWW/HTTP
Classifier: Topic :: Software Development :: Libraries :: Python Modules
Requires-Dist: asgiref (>=3.8.1,<4.0.0)
Requires-Dist: cachetools (>=5.3.3,<6.0.0)
Requires-Dist: charset-normalizer (>=3.3.2,<4.0.0)
Requires-Dist: importlib (>=1.0.4,<2.0.0)
Requires-Dist: requests (>=2.31.0,<3.0.0)
Requires-Dist: rsa (>=4.9,<5.0)
Project-URL: Repository, https://github.com/mdsol/mauth-client-python
